quickstockdata/__init__.py
quickstockdata/indian.py
quickstockdata/stock_apis.py
quickstockdata/usa.py
quickstockdata-0.1.7.dist-info/METADATA
quickstockdata-0.1.7.dist-info/WHEEL
quickstockdata-0.1.7.dist-info/RECORD
