Metadata-Version: 2.1
Name: quickstockdata
Version: 0.1.7
Summary: 
Author: princedhamecha_crest
Author-email: prince.dhamecha@crestdatasys.com
Requires-Python: >=3.9,<4.0
Classifier: Programming Language :: Python :: 3
Classifier: Programming Language :: Python :: 3.9
Classifier: Programming Language :: Python :: 3.10
Classifier: Programming Language :: Python :: 3.11
Classifier: Programming Language :: Python :: 3.12
Requires-Dist: requests (>=2.31.0,<3.0.0)
